topsis_angadSingh_102203314/__init__.py
topsis_angadSingh_102203314/main.py
topsis_angadSingh_102203314-1.0.0.dist-info/LICENCE
topsis_angadSingh_102203314-1.0.0.dist-info/METADATA
topsis_angadSingh_102203314-1.0.0.dist-info/WHEEL
topsis_angadSingh_102203314-1.0.0.dist-info/entry_points.txt
topsis_angadSingh_102203314-1.0.0.dist-info/top_level.txt
topsis_angadSingh_102203314-1.0.0.dist-info/RECORD
