Metadata-Version: 2.2
Name: topsis_angadSingh_102203314
Version: 1.0.0
Summary: A Python package to perform TOPSIS analysis on datasets.
Home-page: https://github.com/Angad8285/topsis_angadSingh_102203314
Author: Angad Singh
Author-email: angads140101@gmail.com
Classifier: Programming Language :: Python :: 3
Classifier: License :: OSI Approved :: MIT License
Classifier: Operating System :: OS Independent
Requires-Python: >=3.6
License-File: LICENCE
Requires-Dist: pandas>=1.0.0
Dynamic: author
Dynamic: author-email
Dynamic: classifier
Dynamic: description
Dynamic: description-content-type
Dynamic: home-page
Dynamic: requires-dist
Dynamic: requires-python
Dynamic: summary
